{
  "Top": "inverter",
  "RtlTop": "inverter",
  "RtlPrefix": "",
  "SourceLanguage": "cpp",
  "ResetStyle": "control",
  "GenerateBdFiles": "1",
  "HostMachineBits": "64",
  "Target": {
    "Family": "zynq",
    "Device": "xc7z020",
    "Package": "-clg484",
    "Speed": "-1"
  },
  "HlsSolution": {"Config": [
      "config_export -format=ip_catalog",
      "config_export -rtl=vhdl"
    ]},
  "Args": {
    "s_axis_video": {
      "index": "0",
      "type": {
        "kinds": ["struct"],
        "dataType": "ap_axiu<8, 1, 1, 1>",
        "structImpl": "flat-field",
        "dataPack": true,
        "fields": {
          "data": {
            "order": "0",
            "dataType": "ap_uint"
          },
          "keep": {
            "order": "1",
            "dataType": "ap_uint"
          },
          "strb": {
            "order": "2",
            "dataType": "ap_uint"
          },
          "user": {
            "order": "3",
            "dataType": "ap_uint"
          },
          "last": {
            "order": "4",
            "dataType": "ap_uint"
          },
          "id": {
            "order": "5",
            "dataType": "ap_uint"
          },
          "dest": {
            "order": "6",
            "dataType": "ap_uint"
          }
        }
      }
    },
    "m_axis_video": {
      "index": "1",
      "type": {
        "kinds": ["struct"],
        "dataType": "ap_axiu<8, 1, 1, 1>",
        "structImpl": "flat-field",
        "dataPack": true,
        "fields": {
          "data": {
            "order": "0",
            "dataType": "ap_uint"
          },
          "keep": {
            "order": "1",
            "dataType": "ap_uint"
          },
          "strb": {
            "order": "2",
            "dataType": "ap_uint"
          },
          "user": {
            "order": "3",
            "dataType": "ap_uint"
          },
          "last": {
            "order": "4",
            "dataType": "ap_uint"
          },
          "id": {
            "order": "5",
            "dataType": "ap_uint"
          },
          "dest": {
            "order": "6",
            "dataType": "ap_uint"
          }
        }
      }
    },
    "VidOrig_nVideoInv": {
      "index": "2",
      "type": {
        "dataType": "ap_uint",
        "dataWidth": "1",
        "interfaceRef": "VidOrig_nVideoInv_V"
      }
    }
  },
  "Return": {
    
  },
  "ClockInfo": {
    "ClockName": "ap_clk",
    "ClockPeriod": "10",
    "IsCombLogic": "0",
    "II": "x",
    "Latency": "1",
    "Uncertainty": "1.25"
  },
  "Xdc": {"OocClocks": ["create_clock -name ap_clk -period 10.000 [get_ports ap_clk]"]},
  "Ipx": {
    "Vendor": "xilinx.com",
    "Library": "hls",
    "Name": "inverter",
    "Version": "1.0",
    "DisplayName": "Inverter",
    "Revision": "",
    "Description": "An IP generated by Vivado HLS",
    "Taxonomy": "\/VIVADO_HLS_IP",
    "AutoFamilySupport": ""
  },
  "Files": {
    "CSource": ["..\/inverter.cpp"],
    "Vhdl": [
      "impl\/vhdl\/regslice_core.vhd",
      "impl\/vhdl\/inverter.vhd"
    ],
    "Verilog": [
      "impl\/verilog\/regslice_core.v",
      "impl\/verilog\/inverter.v"
    ],
    "Misc": ["impl\/misc\/logo.png"],
    "DesignXml": "C:\/Users\/ap576391\/Documents\/TP_DUBOIS\/ip_repo\/inverter\/solution1\/.autopilot\/db\/inverter.design.xml",
    "DebugDir": "C:\/Users\/ap576391\/Documents\/TP_DUBOIS\/ip_repo\/inverter\/solution1\/.debug",
    "ProtoInst": ["C:\/Users\/ap576391\/Documents\/TP_DUBOIS\/ip_repo\/inverter\/solution1\/.debug\/inverter.protoinst"]
  },
  "SubcoreInfo": {
    "HasXpmMemory": false,
    "HasClockedDsp": false,
    "IP": []
  },
  "Interfaces": {
    "ap_clk": {
      "type": "clock",
      "ctype": {"CLK": {"Type": "bool"}},
      "bundle_name": "ap_clk",
      "bundle_role": "default",
      "buses": "s_axis_video m_axis_video",
      "reset": "ap_rst_n"
    },
    "ap_ctrl": {
      "type": "ap_ctrl",
      "ctrl_ports": "ap_start ap_done ap_idle ap_ready",
      "ctype": {
        "start": {"Type": "bool"},
        "done": {"Type": "bool"},
        "idle": {"Type": "bool"},
        "ready": {"Type": "bool"}
      }
    },
    "ap_rst_n": {
      "type": "reset",
      "polarity": "ACTIVE_LOW",
      "ctype": {"RST": {"Type": "bool"}},
      "bundle_name": "ap_rst_n",
      "bundle_role": "default"
    },
    "m_axis_video": {
      "type": "axi4stream",
      "mode": "master",
      "port_prefix": "m_axis_video",
      "has_tready": "1",
      "ctype": {
        "TDATA": {
          "Type": "integer unsigned",
          "Width": "8"
        },
        "TVALID": {"Type": "bool"},
        "TREADY": {"Type": "bool"},
        "TDEST": {
          "Type": "integer unsigned",
          "Width": "1"
        },
        "TKEEP": {
          "Type": "integer unsigned",
          "Width": "1"
        },
        "TSTRB": {
          "Type": "integer unsigned",
          "Width": "1"
        },
        "TUSER": {
          "Type": "integer unsigned",
          "Width": "1"
        },
        "TLAST": {
          "Type": "integer unsigned",
          "Width": "1"
        },
        "TID": {
          "Type": "integer unsigned",
          "Width": "1"
        }
      },
      "port_width": {
        "TDATA": "8",
        "TDEST": "1",
        "TID": "1",
        "TKEEP": "1",
        "TLAST": "1",
        "TSTRB": "1",
        "TUSER": "1"
      }
    },
    "s_axis_video": {
      "type": "axi4stream",
      "mode": "slave",
      "port_prefix": "s_axis_video",
      "has_tready": "1",
      "ctype": {
        "TDATA": {
          "Type": "integer unsigned",
          "Width": "8"
        },
        "TVALID": {"Type": "bool"},
        "TREADY": {"Type": "bool"},
        "TDEST": {
          "Type": "integer unsigned",
          "Width": "1"
        },
        "TKEEP": {
          "Type": "integer unsigned",
          "Width": "1"
        },
        "TSTRB": {
          "Type": "integer unsigned",
          "Width": "1"
        },
        "TUSER": {
          "Type": "integer unsigned",
          "Width": "1"
        },
        "TLAST": {
          "Type": "integer unsigned",
          "Width": "1"
        },
        "TID": {
          "Type": "integer unsigned",
          "Width": "1"
        }
      },
      "port_width": {
        "TDATA": "8",
        "TDEST": "1",
        "TID": "1",
        "TKEEP": "1",
        "TLAST": "1",
        "TSTRB": "1",
        "TUSER": "1"
      }
    },
    "VidOrig_nVideoInv_V": {
      "type": "data",
      "dir": "in",
      "width": "1",
      "ctype": {"DATA": {
          "Type": "integer unsigned",
          "Width": "1"
        }},
      "bundle_name": "VidOrig_nVideoInv_V",
      "bundle_role": "default"
    }
  },
  "RtlPorts": {
    "ap_clk": {
      "dir": "in",
      "width": "1"
    },
    "ap_rst_n": {
      "dir": "in",
      "width": "1"
    },
    "ap_start": {
      "dir": "in",
      "width": "1"
    },
    "ap_done": {
      "dir": "out",
      "width": "1"
    },
    "ap_idle": {
      "dir": "out",
      "width": "1"
    },
    "ap_ready": {
      "dir": "out",
      "width": "1"
    },
    "s_axis_video_TDATA": {
      "dir": "in",
      "width": "8"
    },
    "s_axis_video_TVALID": {
      "dir": "in",
      "width": "1"
    },
    "s_axis_video_TREADY": {
      "dir": "out",
      "width": "1"
    },
    "s_axis_video_TDEST": {
      "dir": "in",
      "width": "1",
      "isVector": "true"
    },
    "s_axis_video_TKEEP": {
      "dir": "in",
      "width": "1",
      "isVector": "true"
    },
    "s_axis_video_TSTRB": {
      "dir": "in",
      "width": "1",
      "isVector": "true"
    },
    "s_axis_video_TUSER": {
      "dir": "in",
      "width": "1",
      "isVector": "true"
    },
    "s_axis_video_TLAST": {
      "dir": "in",
      "width": "1",
      "isVector": "true"
    },
    "s_axis_video_TID": {
      "dir": "in",
      "width": "1",
      "isVector": "true"
    },
    "m_axis_video_TDATA": {
      "dir": "out",
      "width": "8"
    },
    "m_axis_video_TVALID": {
      "dir": "out",
      "width": "1"
    },
    "m_axis_video_TREADY": {
      "dir": "in",
      "width": "1"
    },
    "m_axis_video_TDEST": {
      "dir": "out",
      "width": "1",
      "isVector": "true"
    },
    "m_axis_video_TKEEP": {
      "dir": "out",
      "width": "1",
      "isVector": "true"
    },
    "m_axis_video_TSTRB": {
      "dir": "out",
      "width": "1",
      "isVector": "true"
    },
    "m_axis_video_TUSER": {
      "dir": "out",
      "width": "1",
      "isVector": "true"
    },
    "m_axis_video_TLAST": {
      "dir": "out",
      "width": "1",
      "isVector": "true"
    },
    "m_axis_video_TID": {
      "dir": "out",
      "width": "1",
      "isVector": "true"
    },
    "VidOrig_nVideoInv_V": {
      "dir": "in",
      "width": "1",
      "isVector": "true"
    }
  },
  "ModuleInfo": {
    "Hierarchy": {"ModuleName": "inverter"},
    "Info": {"inverter": {
        "FunctionProtocol": "ap_ctrl_hs",
        "isTaskLevelControl": "1",
        "isPipelined": "0",
        "isCombinational": "0",
        "isOneStateSeq": "0"
      }},
    "Metrics": {"inverter": {
        "Latency": {
          "LatencyBest": "1",
          "LatencyAvg": "1",
          "LatencyWorst": "1",
          "PipelineII": "2",
          "PipelineDepth": "",
          "PipelineType": "none"
        },
        "Timing": {
          "Target": "10.00",
          "Uncertainty": "1.25",
          "Estimate": "1.248"
        },
        "Area": {
          "FF": "2",
          "LUT": "51",
          "BRAM_18K": "0",
          "DSP48E": "0",
          "URAM": "0"
        }
      }}
  },
  "Sdx": {
    "Target": "none",
    "ProfileOption": "0",
    "ProfileType": "none",
    "XO": "",
    "KernelName": "inverter",
    "EnableXoSwEmu": "1"
  },
  "GenData": {
    "DataVersion": "0.2",
    "Time": "2023-11-08 11:55:38 +0100",
    "ToolName": "vivado_hls",
    "ToolVersion": "2019.2"
  }
}
